Workbook

Sheet Cover
B4: PERISHABLE FARMS CANADA
B5: Supply Chain Cost Analysis Model
B6: Commodity: Fresh Tomatoes | Route: Ontario Farm → Toronto Wholesale Market
B10: Prepared by: | C10: Your Name
B11: Date: | C11: June 2025
B12: Version: | C12: 1.0
B13: Currency: | C13: Canadian Dollar (CAD)
B14: Unit of Analysis: | C14: Per Tonne of Fresh Tomatoes
B16: EXECUTIVE SUMMARY – KEY METRICS
B17: Cost Category | C17: CAD $ / Tonne | D17: % of Total Cost | E17: Notes
B18: 1. Farm Input Costs | C18: ='Farm Inputs'!C28 -> 237.5 | D18: =IFERROR(C18/$C$24,0) -> 0.3650353 | E18: Seeds, labour, irrigation, fertiliser
B19: 2. Harvesting & Packing | C19: ='Harvest & Pack'!C20 -> 148 | D19: =IFERROR(C19/$C$24,0) -> 0.22747463 | E19: Manual + mechanical harvest, grading
B20: 3. Cold Chain & Storage | C20: ='Cold Chain'!C18 -> 100.9 | D20: =IFERROR(C20/$C$24,0) -> 0.15508237 | E20: Pre-cooling, cold storage, reefer transport
B21: 4. Transport & Logistics | C21: =Logistics!C16 -> 73.472 | D21: =IFERROR(C21/$C$24,0) -> 0.11292578 | E21: Truck, fuel, tolls, loading/unloading
B22: 5. Spoilage & Waste | C22: =Spoilage!C14 -> 61.75 | D22: =IFERROR(C22/$C$24,0) -> 0.094909179 | E22: Estimated losses along chain
B23: 6. Admin & Overheads | C23: =Admin!C12 -> 29 | D23: =IFERROR(C23/$C$24,0) -> 0.044572732 | E23: Insurance, compliance, management
B24: TOTAL SUPPLY CHAIN COST | C24: =SUM(C18:C23) -> 650.622 | D24: 1
B26: Market Selling Price (CAD $/tonne) | C26: =Assumptions!C5 -> 950
B27: Gross Margin (CAD $/tonne) | C27: =C26-C24 -> 299.378
B28: Gross Margin % | C28: =IFERROR((C26-C24)/C26,0) -> 0.31513474

Sheet Assumptions
B1: KEY ASSUMPTIONS
B2: All blue cells are editable inputs. Change values to model different scenarios.
B4: MARKET & REVENUE
B5: Market selling price (CAD $/tonne) | C5: 950 | D5: CAD / tonne | E5: Source: AAFC Wholesale Price Report, 2024
B6: Annual production volume (tonnes/year) | C6: 500 | D6: CAD / tonne | E6: Assumed mid-size Ontario greenhouse farm
B7: Market distance – farm to buyer (km) | C7: 180 | D7: CAD / tonne | E7: Toronto Distribution Hub
B9: FARM INPUT RATES
B10: Seed cost (CAD $/tonne output) | C10: 28 | D10: CAD / tonne | E10: Source: Sakata Seed Canada, 2024
B11: Fertiliser & inputs (CAD $/tonne) | C11: 45 | D11: CAD / tonne | E11: NPK + micro-nutrients blend
B12: Irrigation water cost (CAD $/tonne) | C12: 12 | D12: CAD / tonne | E12: Ontario municipal water rate
B13: Labour – growing (CAD $/tonne) | C13: 60 | D13: CAD / tonne | E13: Seasonal worker @ CAD $17/hr
B15: HARVEST & PACKING
B16: Harvest labour (CAD $/tonne) | C16: 35 | D16: CAD / tonne | E16: Manual picking @ $17/hr
B17: Packaging materials (CAD $/tonne) | C17: 22 | D17: CAD / tonne | E17: 20 kg clamshell trays
B18: Grading & quality check (CAD $/tonne) | C18: 10 | D18: CAD / tonne | E18: CFIA compliant grading line
B20: COLD CHAIN
B21: Pre-cooling (CAD $/tonne) | C21: 18 | D21: CAD / tonne | E21: Forced-air cooling to 10°C
B22: Cold storage – daily rate (CAD $/tonne/day) | C22: 2.5 | D22: CAD / tonne | E22: 3 days average holding
B23: Avg. cold storage days | C23: 3 | D23: CAD / tonne | E23: Farm to truck
B24: Refrigerated transport (CAD $/km/tonne) | C24: 0.38 | D24: CAD / tonne | E24: Reefer truck, 180 km route
B26: LOGISTICS
B27: Fuel surcharge % on transport | C27: 0.08 | D27: CAD / tonne | E27: Canadian Trucking Alliance avg.
B28: Loading/unloading (CAD $/tonne) | C28: 14 | D28: CAD / tonne | E28: Unionised dock labour
B29: Toll & highway fees (CAD $/tonne) | C29: 4 | D29: CAD / tonne | E29: 407 ETR estimate
B30: Broker/commission fee % | C30: 0.05 | D30: CAD / tonne | E30: Wholesale market commission
B32: SPOILAGE
B33: Farm-level spoilage rate | C33: 0.03 | D33: CAD / tonne | E33: Defects, culls
B34: Transit spoilage rate | C34: 0.02 | D34: CAD / tonne | E34: Temperature excursions
B35: Market spoilage rate | C35: 0.015 | D35: CAD / tonne | E35: Unsold/rejected at buyer
B37: ADMIN & OVERHEAD
B38: Insurance (CAD $/tonne) | C38: 8 | D38: CAD / tonne | E38: Crop + liability insurance
B39: Regulatory compliance (CAD $/tonne) | C39: 6 | D39: CAD / tonne | E39: CFIA, FSEP, Safe Food Canada
B40: Management overhead (CAD $/tonne) | C40: 15 | D40: CAD / tonne | E40: 10% GM salary allocation

Sheet Farm Inputs
B1: 1. Farm Input Costs
B2: Cost Item | C2: CAD $ / Tonne | D2: % of Total Cost | E2: Notes / Formula Basis
B3: Seeds | C3: =Assumptions!C10 -> 28 | D3: =IFERROR(C3/$C$28,0) -> 0.11789474 | E3: Sakata hybrid tomato seed, CAD $28/tonne output
B4: Fertilisers & Soil Amendments | C4: =Assumptions!C11 -> 45 | D4: =IFERROR(C4/$C$28,0) -> 0.18947368 | E4: NPK 20-10-20 + calcium nitrate foliar
B5: Irrigation Water | C5: =Assumptions!C12 -> 12 | D5: =IFERROR(C5/$C$28,0) -> 0.050526316 | E5: Municipal water @ metered rate
B6: Pesticides & Fungicides | C6: =15 -> 15 | D6: =IFERROR(C6/$C$28,0) -> 0.063157895 | E6: IPM programme – reduced chemical regime
B7: Greenhouse Energy (heating/lighting) | C7: =32 -> 32 | D7: =IFERROR(C7/$C$28,0) -> 0.13473684 | E7: Natural gas + LED supplemental lighting
B8: Growing Labour | C8: =Assumptions!C13 -> 60 | D8: =IFERROR(C8/$C$28,0) -> 0.25263158 | E8: Seasonal workers, 8 hrs/day, CAD $17/hr
B9: Equipment Depreciation | C9: =18 -> 18 | D9: =IFERROR(C9/$C$28,0) -> 0.075789474 | E9: Tractors, irrigation pumps – 10-yr straight-line
B10: Land / Greenhouse Lease | C10: =25 -> 25 | D10: =IFERROR(C10/$C$28,0) -> 0.10526316 | E10: Leasehold charge allocated per tonne
B11: Crop Insurance Premium | C11: =Assumptions!C22 -> 2.5 | D11: =IFERROR(C11/$C$28,0) -> 0.010526316 | E11: AgriInsurance – OMAFRA programme
B28: TOTAL – 1. Farm Input Costs | C28: =SUM(C3:C27) -> 237.5 | D28: 1

Sheet Harvest & Pack
B1: 2. Harvesting & Packing
B2: Cost Item | C2: CAD $ / Tonne | D2: % of Total Cost | E2: Notes / Formula Basis
B3: Harvest Labour | C3: =Assumptions!C16 -> 35 | D3: =IFERROR(C3/$C$20,0) -> 0.23648649 | E3: Hand-picking @ CAD $17/hr, 2.5 hrs/tonne
B4: Mechanical Harvesting Aids | C4: =Assumptions!C17 -> 22 | D4: =IFERROR(C4/$C$20,0) -> 0.14864865 | E4: Platform trolleys, conveyor rental
B5: Grading & Quality Inspection | C5: =Assumptions!C18 -> 10 | D5: =IFERROR(C5/$C$20,0) -> 0.067567568 | E5: CFIA Grade A/B sorting line
B6: Packaging Materials | C6: =Assumptions!C13 -> 60 | D6: =IFERROR(C6/$C$20,0) -> 0.40540541 | E6: 20 kg clamshell, printed label, pallet wrap
B7: Packing Labour | C7: =12 -> 12 | D7: =IFERROR(C7/$C$20,0) -> 0.081081081 | E7: Packing line workers @ $17/hr
B8: Quality Sampling & Lab Tests | C8: =5 -> 5 | D8: =IFERROR(C8/$C$20,0) -> 0.033783784 | E8: Pesticide residue + Brix tests
B9: Waste Disposal – culls | C9: =4 -> 4 | D9: =IFERROR(C9/$C$20,0) -> 0.027027027 | E9: Composting / landfill tipping fees
B20: TOTAL – 2. Harvesting & Packing | C20: =SUM(C3:C19) -> 148 | D20: 1

Sheet Cold Chain
B1: 3. Cold Chain & Storage
B2: Cost Item | C2: CAD $ / Tonne | D2: % of Total Cost | E2: Notes / Formula Basis
B3: Pre-Cooling (forced-air to 10°C) | C3: =Assumptions!C21 -> 18 | D3: =IFERROR(C3/$C$18,0) -> 0.17839445 | E3: Electricity + labour for cooling room
B4: Cold Storage – holding cost | C4: =Assumptions!C22*Assumptions!C23 -> 7.5 | D4: =IFERROR(C4/$C$18,0) -> 0.074331021 | E4: Rate × avg. days held
B5: Refrigerated Transport (reefer) | C5: =Assumptions!C24*Assumptions!C7 -> 68.4 | D5: =IFERROR(C5/$C$18,0) -> 0.67789891 | E5: CAD $/km × 180 km route
B6: Cold Chain Monitoring (IoT sensors) | C6: =3 -> 3 | D6: =IFERROR(C6/$C$18,0) -> 0.029732408 | E6: Temperature loggers + cloud platform
B7: Emergency Cold Storage (buffer) | C7: =4 -> 4 | D7: =IFERROR(C7/$C$18,0) -> 0.039643211 | E7: Overflow capacity @ third-party facility
B18: TOTAL – 3. Cold Chain & Storage | C18: =SUM(C3:C17) -> 100.9 | D18: 1

Sheet Logistics
B1: 4. Transport & Logistics
B2: Cost Item | C2: CAD $ / Tonne | D2: % of Total Cost | E2: Notes / Formula Basis
B3: Base Freight Cost | C3: =Assumptions!C19*Assumptions!C3 -> 0 | D3: =IFERROR(C3/$C$16,0) -> 0 | E3: Rate × distance – see Cold Chain
B4: Fuel Surcharge | C4: =Assumptions!C27*(Assumptions!C24*Assumptions!C7) -> 5.472 | D4: =IFERROR(C4/$C$16,0) -> 0.074477352 | E4: FSC % × base freight
B5: Loading & Unloading Labour | C5: =Assumptions!C21 -> 18 | D5: =IFERROR(C5/$C$16,0) -> 0.24499129 | E5: Dock labour, unionised rate
B6: Toll & Highway Fees | C6: =Assumptions!C22 -> 2.5 | D6: =IFERROR(C6/$C$16,0) -> 0.034026568 | E6: 407 ETR + 400-series highways
B7: Wholesale Broker Commission | C7: =Assumptions!C30*Assumptions!C5 -> 47.5 | D7: =IFERROR(C7/$C$16,0) -> 0.64650479 | E7: Commission % × selling price
B16: TOTAL – 4. Transport & Logistics | C16: =SUM(C3:C15) -> 73.472 | D16: 1

Sheet Spoilage
B1: 5. Spoilage & Waste Losses
B2: Cost Item | C2: CAD $ / Tonne | D2: % of Total Cost | E2: Notes / Formula Basis
B3: Farm-level losses (culls, defects) | C3: =Assumptions!C33*Assumptions!C5 -> 28.5 | D3: =IFERROR(C3/$C$6,0) -> 0 | E3: Farm spoilage rate × selling price
B4: Transit losses (temperature/bruising) | C4: =Assumptions!C34*Assumptions!C5 -> 19 | D4: =IFERROR(C4/$C$6,0) -> 0 | E4: Transit spoilage rate × selling price
B5: Market/buyer rejection losses | C5: =Assumptions!C35*Assumptions!C5 -> 14.25 | D5: =IFERROR(C5/$C$6,0) -> 0 | E5: Market spoilage rate × selling price
B14: TOTAL – 5. Spoilage & Waste Losses | C14: =SUM(C3:C13) -> 61.75 | D14: 1

Sheet Admin
B1: 6. Administration & Overheads
B2: Cost Item | C2: CAD $ / Tonne | D2: % of Total Cost | E2: Notes / Formula Basis
B3: Insurance (crop + liability) | C3: =Assumptions!C38 -> 8 | D3: =IFERROR(C3/$C$12,0) -> 0.27586207 | E3: AgriCorp crop insurance + farm liability
B4: Regulatory & Compliance | C4: =Assumptions!C39 -> 6 | D4: =IFERROR(C4/$C$12,0) -> 0.20689655 | E4: CFIA, Safe Food for Canadians Act fees
B5: Management & Administration | C5: =Assumptions!C40 -> 15 | D5: =IFERROR(C5/$C$12,0) -> 0.51724138 | E5: GM salary + office overhead per tonne
B12: TOTAL – 6. Administration & Overheads | C12: =SUM(C3:C11) -> 29 | D12: 1

Sheet Scenario Analysis
B1: SCENARIO ANALYSIS – SENSITIVITY TABLE
B2: Change the selling price and spoilage rate to see impact on gross margin.
B4: Metric | C4: Base Case | D4: Scenario A (Low Price) | E4: Scenario B (High Spoilage) | F4: Scenario C (Cost Increase) | G4: Scenario D (Optimistic)
B5: Selling Price (CAD $/t) | C5: =Assumptions!C5 -> 950 | D5: 800 | E5: =Assumptions!C5 -> 950 | F5: 1000 | G5: 1050
B6: Total Supply Chain Cost (CAD $/t) | C6: =Cover!C24 -> 650.622 | D6: =Cover!C24 -> 650.622 | E6: =Cover!C24*1.08 -> 702.67176 | F6: =Cover!C24*1.12 -> 728.69664 | G6: =Cover!C24*0.95 -> 618.0909
B7: Gross Margin (CAD $/t) | C7: =C5-C6 -> 299.378 | D7: =D5-D6 -> 149.378 | E7: =E5-E6 -> 247.32824 | F7: =F5-F6 -> 271.30336 | G7: =G5-G6 -> 431.9091
B8: Gross Margin % | C8: =IFERROR(C7/C5,0) -> 0.31513474 | D8: =IFERROR(D7/D5,0) -> 0.1867225 | E8: =IFERROR(E7/E5,0) -> 0.26034552 | F8: =IFERROR(F7/F5,0) -> 0.27130336 | G8: =IFERROR(G7/G5,0) -> 0.411342
B11: HOW TO USE THIS TABLE
B12: • Scenario A: Price falls to CAD $800/t (poor harvest season / market glut) – observe margin compression.
B13: • Scenario B: Total costs rise 8% (higher fuel, labour) – models inflationary pressure on supply chain.
B14: • Scenario C: Full 12% cost shock (energy crisis / supply disruption) – stress-test of farm viability.
B15: • Scenario D: Optimistic – 5% cost reduction (efficiency gains, scale) with premium price point.
B16: • To add your own scenario: copy a column, change the blue input cells, and update the formulas.
